{
  "appenders": {
    "stdout": {
      "type": "stdout"
    },
    "moguraDateFile": {
      "type": "dateFile",
      "filename": "./logs/mogura.log",
      "pattern": "-yyyyMMdd"
    },
    "dirWalkerDateFile": {
      "type": "dateFile",
      "filename": "./logs/dir_walker.log",
      "pattern": "-yyyyMMdd"
    },
    "utilsDateFile": {
      "type": "dateFile",
      "filename": "./logs/utils.log",
      "pattern": "-yyyyMMdd"
    }
  },
  "categories": {
    "default": {
      "appenders": [ "stdout" ],
      "level": "debug"
    },
    "mogura": {
      "appenders": [ "moguraDateFile", "stdout" ],
      "level": "debug"
    },
    "mogura_list": {
      "appenders": [],
      "level": "debug"
    },
    "dir_walker": {
      "appenders": [ "dirWalkerDateFile" ],
      "level": "debug"
    },
    "utils": {
      "appenders": [ "utilsDateFile" ],
      "level": "debug"
    }
  }
}
